netbox_ipmi_ovh/__init__.py
netbox_ipmi_ovh/exceptions.py
netbox_ipmi_ovh/forms.py
netbox_ipmi_ovh/ipmi.py
netbox_ipmi_ovh/models.py
netbox_ipmi_ovh/navigation.py
netbox_ipmi_ovh/template_content.py
netbox_ipmi_ovh/urls.py
netbox_ipmi_ovh/views.py
netbox_ipmi_ovh/migrations/0001_initial.py
netbox_ipmi_ovh/migrations/__init__.py
netbox_ipmi_ovh/templates/netbox_ipmi_ovh/ipmi_button.html
netbox_ipmi_ovh/templates/netbox_ipmi_ovh/ipmi_button_3.x.html
netbox_ipmi_ovh/templates/netbox_ipmi_ovh/ipmi_config.html
netbox_ipmi_ovh/templates/netbox_ipmi_ovh/ipmi_config_3.x.html
netbox_ipmi_ovh/templates/netbox_ipmi_ovh/ipmi_error.html
netbox_ipmi_ovh/templates/netbox_ipmi_ovh/ipmi_error_3.x.html
netbox_ipmi_ovh-1.0.2.dist-info/LICENSE
netbox_ipmi_ovh-1.0.2.dist-info/METADATA
netbox_ipmi_ovh-1.0.2.dist-info/WHEEL
netbox_ipmi_ovh-1.0.2.dist-info/top_level.txt
netbox_ipmi_ovh-1.0.2.dist-info/RECORD
