Metadata-Version: 2.1
Name: netbox-ipmi-ovh
Version: 1.0.2
Summary: A tool to launch ipmi for ovh servers without going through the manager
Home-page: https://github.com/sanecz/netbox-ipmi-ovh
Author: Lisa Bekdache
Author-email: lisa.bekdache@gmail.com
License: MIT
Download-URL: https://github.com/sanecz/netbox-ipmi-ovh/archive/v1.0.2.tar.gz
Keywords: netbox,netbox-plugin,plugin
Platform: UNKNOWN
Classifier: Development Status :: 4 - Beta
Classifier: Programming Language :: Python :: 3
Classifier: Programming Language :: Python :: 3.7
Classifier: Programming Language :: Python :: 3.8
Classifier: Programming Language :: Python :: 3.9
License-File: LICENSE
Requires-Dist: ovh
